supSMSTAS/UI.py
supSMSTAS/WFC.py
supSMSTAS/__init__.py
supSMSTAS/__main__.py
supSMSTAS/shape.py
supSMSTAS/codes/showHitbox.bin
supSMSTAS-0.0.1.2.dist-info/COPYING
supSMSTAS-0.0.1.2.dist-info/METADATA
supSMSTAS-0.0.1.2.dist-info/WHEEL
supSMSTAS-0.0.1.2.dist-info/entry_points.txt
supSMSTAS-0.0.1.2.dist-info/top_level.txt
supSMSTAS-0.0.1.2.dist-info/RECORD
