Metadata-Version: 2.1
Name: supSMSTAS
Version: 0.0.1.2
Summary: A tool to support Super Mario Sunshine Tool Assisted Speedrun/Superplay
Home-page: https://github.com/sup39/supSMSTAS
Author: sup39
Author-email: sms@sup39.dev
License: GPLv3
Project-URL: Bug Tracker, https://github.com/sup39/supSMSTAS/issues
Classifier: Programming Language :: Python :: 3
Classifier: License :: OSI Approved :: GNU General Public License v3 (GPLv3)
Classifier: Operating System :: OS Independent
Requires-Python: >=3.8
Requires-Dist: sup-dolphin-memory-lib (>=0.1.2)
Requires-Dist: matplotlib (>=3.5)
Requires-Dist: PyQt5 (>=5.15)
